MANIFEST.in
README.rst
requirements.txt
setup.cfg
setup.py
reportes_sic/__init__.py
reportes_sic/__init__.pyc
reportes_sic.egg-info/PKG-INFO
reportes_sic.egg-info/SOURCES.txt
reportes_sic.egg-info/dependency_links.txt
reportes_sic.egg-info/top_level.txt
reportes_sic/Compras/Reportes/COMPRAS CON XML.rtm
reportes_sic/Compras/Reportes/IMPUESTOS ARTICULOS.rtm
reportes_sic/Contabilidad/Reportes/DIOT TOTALES.rtm
reportes_sic/Contabilidad/Reportes/DIOT.rtm
reportes_sic/Cuentas por Cobrar/Reportes/CARGOS Y REMISIONES POR CLIENTE.rtm
reportes_sic/Cuentas por Cobrar/Reportes/CARGOS Y REMISIONES POR GRUPO.rtm
reportes_sic/Cuentas por Cobrar/Reportes/COMISIONES.rtm
reportes_sic/Cuentas por Cobrar/Reportes/COMISIONES_DIN.rtm
reportes_sic/Cuentas por Cobrar/Reportes/IMPUESTOS COBROS V Y PV.rtm
reportes_sic/Cuentas por Cobrar/Reportes/IMPUESTOS COBROS.rtm
reportes_sic/Cuentas por Cobrar/Reportes/IMPUESTOS PAGOS PROVEEDORES.rtm
reportes_sic/Cuentas por Cobrar/Reportes/SALDOS DE CLIENTES.rtm
reportes_sic/Cuentas por Cobrar/Reportes/TOTALES DE SALDOS DE CLIENTES.rtm
reportes_sic/Inventarios/Reportes/EXISTENCIAS.rtm
reportes_sic/Inventarios/Reportes/PUNTOS DE REORDEN EXCEDIDOS.rtm
reportes_sic/Punto de venta/Reportes/COBROS Y DEVOLUCIONES PV.rtm
reportes_sic/Punto de venta/Reportes/CORTE AGRUPADO POR FACTURA.rtm
reportes_sic/Punto de venta/Reportes/CORTE.rtm
reportes_sic/Punto de venta/Reportes/IMPUESTOS FACTURAS ARTICULOS AGRUPADOS.rtm
reportes_sic/Punto de venta/Reportes/IMPUESTOS FACTURAS.rtm
reportes_sic/Utilerias/CAMBIA MARGENES EN COMPRAS.sql
reportes_sic/Utilerias/DESCUENTO POR TOTAL DE COMPRA.sql
reportes_sic/Utilerias/DESCUENTO POR VOLUMEN AUTOMATICO.sql
reportes_sic/Utilerias/EVITA BORRAR COMODIN.sql
reportes_sic/Utilerias/VALIDA FOLIO DUPLICADO COMPRAS.sql
reportes_sic/Utilerias/VALIDA FOLIO XMLS COMPRAS.sql
reportes_sic/Ventas/Reportes/ARTICULOS SIN PRECIO.rtm
reportes_sic/Ventas/Reportes/COBROS Y DEVOLUCIONES.rtm
reportes_sic/Ventas/Reportes/IMPUESTOS FACTURAS.rtm